technical_analysis/__init__.py
technical_analysis/main.py
technical_analysis/ta_calculation.py
technical_analysis/technicals.py
technopulse-0.5.0.dist-info/LICENSE
technopulse-0.5.0.dist-info/METADATA
technopulse-0.5.0.dist-info/WHEEL
technopulse-0.5.0.dist-info/top_level.txt
technopulse-0.5.0.dist-info/RECORD
