Metadata-Version: 2.1
Name: technopulse
Version: 0.5.0
Summary: A comprehensive Python library for technical analysis of financial markets
Home-page: https://github.com/sagar9187/technical_analysis
Author: Sagar Jadhav
Author-email: jadhavsagar750@gmail.com
Keywords: technical-analysis finance trading stock-market crypto forex indicators
Classifier: Programming Language :: Python :: 3
Classifier: License :: OSI Approved :: MIT License
Classifier: Operating System :: OS Independent
Classifier: Intended Audience :: Financial and Insurance Industry
Classifier: Topic :: Software Development :: Libraries
Classifier: Topic :: Office/Business :: Financial
Requires-Python: >=3.7
License-File: LICENSE
Requires-Dist: numpy>=1.21.0
Requires-Dist: pandas>=1.3.0
Requires-Dist: yfinance>=0.2.0
Requires-Dist: ta>=0.10.1
